betfair_data-0.3.4.dist-info/METADATA
betfair_data-0.3.4.dist-info/WHEEL
betfair_data-0.3.4.dist-info/license_files/LICENSE
betfair_data/betfair_data.pyi
betfair_data/bflw.pyi
betfair_data/__init__.py
betfair_data/betfair_data.pyd
betfair_data-0.3.4.dist-info/RECORD
