Metadata-Version: 2.1
Name: betfair_data
Version: 0.3.4
Classifier: Programming Language :: Rust
Classifier: Programming Language :: Python :: Implementation :: CPython
Classifier: Programming Language :: Python :: Implementation :: PyPy
License-File: LICENSE
Summary: Fast Python Betfair historic data file parser
Author-email: Robert Tarbath <rtarbath@gmail.com>
Requires-Python: >=3.7
Project-URL: repository, https://github.com/tarb/betfair_data
Project-URL: homepage, https://github.com/tarb/betfair_data
